okws/__init__.py
okws/client.py
okws/config.py
okws/interceptor.py
okws/okex.py
okws/redis.py
okws/server.py
okws/settings.py
okws/websocket.py
okws/ws2redis/__init__.py
okws/ws2redis/app.py
okws/ws2redis/candle.py
okws/ws2redis/normal.py
okws-0.1.2.dist-info/LICENSE
okws-0.1.2.dist-info/METADATA
okws-0.1.2.dist-info/WHEEL
okws-0.1.2.dist-info/top_level.txt
okws-0.1.2.dist-info/RECORD
