Metadata-Version: 2.1
Name: okws
Version: 0.1.2
Summary: 通过 redis 提供 okex websocket 服务数据
Home-page: https://github.com/oscnet/okws
Author: oscnet
Author-email: oscnet@163.com
License: MIT
Keywords: exchange websockets api
Platform: UNKNOWN
Classifier: Development Status :: 4 - Beta
Classifier: Intended Audience :: Financial and Insurance Industry
Classifier: Topic :: Office/Business :: Financial
Classifier: License :: OSI Approved :: MIT License
Classifier: Programming Language :: Python :: 3.8
Classifier: Programming Language :: Python :: 3.9
Requires-Dist: asyncio
Requires-Dist: aioredis
Requires-Dist: websockets
Requires-Dist: tenacity
